main.py
jam_student_grade_tracker-0.1.1.dist-info/METADATA
jam_student_grade_tracker-0.1.1.dist-info/WHEEL
jam_student_grade_tracker-0.1.1.dist-info/entry_points.txt
jam_student_grade_tracker-0.1.1.dist-info/top_level.txt
jam_student_grade_tracker-0.1.1.dist-info/RECORD
