Metadata-Version: 2.4
Name: jam-student-grade-tracker
Version: 0.1.1
Summary: A simple CLI jam-student-grade-tracker
Author-email: JamilaYDhedhi <nurjamila1@gmail.com>
Requires-Python: >=3.11
Requires-Dist: rich>=14.0.0
